{
	"AbbrName": "REF1060167E015",
	"Barcode": "REF1060167E015",
	"Dosage": 30,
	"Filetype": "KitInfo",
	"FullName": "REF1060167流感病毒检测试剂盒16人份22",
	"DistillFile": "",
	"AmpFile": "XC2",
	"SpoolList": [
		{
			"AbbrName": "NED",
			"FullName": "腺病毒",
			"DatumMin": 11,
			"DatumMax": 16,
			"CtMin": 40,
			"CtMax": 45,
			"Threshold": 20,
			"CurveColor": "0,139,139",
			"SpecimenNo": 2,
			"SpecimenType": 1,
			"PoolIndex": 0
		},
		{
			"AbbrName": "CY5",
			"FullName": "鼻病毒1",
			"DatumMin": 12,
			"DatumMax": 17,
			"CtMin": 40,
			"CtMax": 45,
			"Threshold": 20,
			"CurveColor": "250,250,210",
			"SpecimenNo": 5,
			"SpecimenType": 1,
			"PoolIndex": 1
		},
		{
			"AbbrName": "FAM",
			"FullName": "甲型流感病毒",
			"DatumMin": 13,
			"DatumMax": 18,
			"CtMin": 40,
			"CtMax": 45,
			"Threshold": 20,
			"CurveColor": "184,134,11",
			"SpecimenNo": 1,
			"SpecimenType": 1,
			"PoolIndex": 2
		},
		{
			"AbbrName": "ROX",
			"FullName": "乙型流感病毒",
			"DatumMin": 14,
			"DatumMax": 19,
			"CtMin": 40,
			"CtMax": 45,
			"Threshold": 20,
			"CurveColor": "47,79,79",
			"SpecimenNo": 4,
			"SpecimenType": 1,
			"PoolIndex": 3
		},
		{
			"AbbrName": "CY5.5",
			"FullName": "副流感病毒",
			"DatumMin": 15,
			"DatumMax": 20,
			"CtMin": 40,
			"CtMax": 45,
			"Threshold": 20,
			"CurveColor": "255,20,147",
			"SpecimenNo": 6,
			"SpecimenType": 1,
			"PoolIndex": 4
		},
		{
			"AbbrName": "JOE",
			"FullName": "人偏肺病毒",
			"DatumMin": 10,
			"DatumMax": 20,
			"CtMin": 40,
			"CtMax": 45,
			"Threshold": 20,
			"CurveColor": "0,0,139",
			"SpecimenNo": 3,
			"SpecimenType": 1,
			"PoolIndex": 5
		}
	],
	"PositiveList": [
		{
			"AbbrName": "TAMA",
			"FullName": "腺病毒",
			"DatumMin": 10,
			"DatumMax": 18,
			"CtMin": 19,
			"CtMax": 22,
			"Threshold": 31,
			"CurveColor": "0,139,139",
			"SpecimenNo": 2,
			"SpecimenType": 4,
			"PoolIndex": 0
		},
		{
			"AbbrName": "CY5",
			"FullName": "鼻病毒1",
			"DatumMin": 101,
			"DatumMax": 201,
			"CtMin": 211,
			"CtMax": 23,
			"Threshold": 32,
			"CurveColor": "250,250,210",
			"SpecimenNo": 5,
			"SpecimenType": 4,
			"PoolIndex": 1
		},
		{
			"AbbrName": "FAM",
			"FullName": "甲型流感病毒",
			"DatumMin": 10,
			"DatumMax": 20,
			"CtMin": 21,
			"CtMax": 45,
			"Threshold": 33,
			"CurveColor": "184,134,11",
			"SpecimenNo": 1,
			"SpecimenType": 4,
			"PoolIndex": 2
		},
		{
			"AbbrName": "ROX",
			"FullName": "乙型流感病毒",
			"DatumMin": 10,
			"DatumMax": 20,
			"CtMin": 21,
			"CtMax": 45,
			"Threshold": 34,
			"CurveColor": "47,79,79",
			"SpecimenNo": 4,
			"SpecimenType": 4,
			"PoolIndex": 3
		},
		{
			"AbbrName": "CY5.5",
			"FullName": "副流感病毒",
			"DatumMin": 10,
			"DatumMax": 20,
			"CtMin": 21,
			"CtMax": 45,
			"Threshold": 35,
			"CurveColor": "255,20,147",
			"SpecimenNo": 6,
			"SpecimenType": 4,
			"PoolIndex": 4
		},
		{
			"AbbrName": "HEX",
			"FullName": "人偏肺病毒",
			"DatumMin": 10,
			"DatumMax": 20,
			"CtMin": 21,
			"CtMax": 45,
			"Threshold": 36,
			"CurveColor": "0,0,139",
			"SpecimenNo": 3,
			"SpecimenType": 4,
			"PoolIndex": 5
		}
	],
	"NegativeList": [
		{
			"AbbrName": "TAMA",
			"FullName": "腺病毒",
			"DatumMin": 11,
			"DatumMax": 16,
			"CtMin": 19,
			"CtMax": 32,
			"Threshold": 21,
			"CurveColor": "0,139,139",
			"SpecimenNo": 2,
			"SpecimenType": 5,
			"PoolIndex": 0
		},
		{
			"AbbrName": "CY5",
			"FullName": "鼻病毒1",
			"DatumMin": 12,
			"DatumMax": 17,
			"CtMin": 19,
			"CtMax": 33,
			"Threshold": 22,
			"CurveColor": "250,250,210",
			"SpecimenNo": 5,
			"SpecimenType": 5,
			"PoolIndex": 1
		},
		{
			"AbbrName": "FAM",
			"FullName": "甲型流感病毒",
			"DatumMin": 13,
			"DatumMax": 18,
			"CtMin": 21,
			"CtMax": 45,
			"Threshold": 23,
			"CurveColor": "184,134,11",
			"SpecimenNo": 1,
			"SpecimenType": 5,
			"PoolIndex": 2
		},
		{
			"AbbrName": "ROX",
			"FullName": "乙型流感病毒",
			"DatumMin": 14,
			"DatumMax": 19,
			"CtMin": 21,
			"CtMax": 45,
			"Threshold": 24,
			"CurveColor": "47,79,79",
			"SpecimenNo": 4,
			"SpecimenType": 5,
			"PoolIndex": 3
		},
		{
			"AbbrName": "CY5.5",
			"FullName": "副流感病毒",
			"DatumMin": 15,
			"DatumMax": 20,
			"CtMin": 21,
			"CtMax": 45,
			"Threshold": 25,
			"CurveColor": "255,20,147",
			"SpecimenNo": 6,
			"SpecimenType": 5,
			"PoolIndex": 4
		},
		{
			"AbbrName": "HEX",
			"FullName": "人偏肺病毒",
			"DatumMin": 10,
			"DatumMax": 20,
			"CtMin": 21,
			"CtMax": 45,
			"Threshold": 26,
			"CurveColor": "0,0,139",
			"SpecimenNo": 3,
			"SpecimenType": 5,
			"PoolIndex": 5
		}
	]
}